falcon_alliance/__init__.py
falcon_alliance/api_client.py
falcon_alliance/plotting/__init__.py
falcon_alliance/plotting/plotter.py
falcon_alliance/schemas/__init__.py
falcon_alliance/schemas/api_status.py
falcon_alliance/schemas/award.py
falcon_alliance/schemas/base_schema.py
falcon_alliance/schemas/event_team_status.py
falcon_alliance/schemas/main_schemas.py
falcon_alliance/schemas/match.py
falcon_alliance/schemas/media.py
falcon_alliance/schemas/robot.py
falcon_alliance/tests/__init__.py
falcon_alliance/tests/district_test.py
falcon_alliance/tests/event_test.py
falcon_alliance/tests/tba_api_client_test.py
falcon_alliance/tests/team_test.py
falcon_alliance/tests/tox_requirements.txt
falcon_alliance/utils/__init__.py
falcon_alliance/utils/exceptions.py
falcon_alliance/utils/functions.py
falcon_alliance/utils/internal_data.py
falcon_alliance-1.0.1.dist-info/LICENSE
falcon_alliance-1.0.1.dist-info/WHEEL
falcon_alliance-1.0.1.dist-info/METADATA
falcon_alliance-1.0.1.dist-info/RECORD
