Metadata-Version: 2.1
Name: falcon-alliance
Version: 1.0.1
Summary: A Pythonic library that attains FRC-related information from sources like The Blue Alliance and more.
Home-page: https://github.com/team4099/FalconAlliance
License: MIT
Author: The Falcons - Team 4099
Author-email: contact@team4099.com
Requires-Python: >=3.8,<4.0
Classifier: License :: OSI Approved :: MIT License
Classifier: Programming Language :: Python :: 3
Classifier: Programming Language :: Python :: 3.10
Classifier: Programming Language :: Python :: 3.8
Classifier: Programming Language :: Python :: 3.9
Requires-Dist: aiohttp (>=3.8.1,<3.9.0)
Requires-Dist: matplotlib (>=3.6.0,<3.7.0)
Requires-Dist: python-dotenv (>=0.19,<1.0)
Requires-Dist: scipy (>=1.9.2,<1.10.0)
Project-URL: Documentation, https://falcon-alliance.readthedocs.io/en/latest
Project-URL: Repository, https://github.com/team4099/FalconAlliance
